setup.py
my_statistics_distributions/Binomialdistribution.py
my_statistics_distributions/Gaussiandistribution.py
my_statistics_distributions/Generaldistribution.py
my_statistics_distributions/__init__.py
my_statistics_distributions.egg-info/PKG-INFO
my_statistics_distributions.egg-info/SOURCES.txt
my_statistics_distributions.egg-info/dependency_links.txt
my_statistics_distributions.egg-info/not-zip-safe
my_statistics_distributions.egg-info/top_level.txt